yu_pytools/_init_.py
yu_pytools/etccdi.py
yu_pytools/ncc.py
yu_pytools/sdd.py
yu_pytools/utils.py
yu_pytools-1.0.0.dist-info/licenses/LICENSE
yu_pytools-1.0.0.dist-info/METADATA
yu_pytools-1.0.0.dist-info/WHEEL
yu_pytools-1.0.0.dist-info/top_level.txt
yu_pytools-1.0.0.dist-info/RECORD
