Metadata-Version: 2.4
Name: yu-pytools
Version: 1.0.0
Summary: Python tools for climate data analysis including ETCCDI, SDD, and NCC modules
Author-email: YuHaoRan <yuhaoran251@mails.ucas.ac.cn>
License: MIT
Requires-Python: >=3.8
License-File: LICENSE
Requires-Dist: numpy>=1.20.0
Requires-Dist: pandas>=1.3.0
Requires-Dist: xarray>=0.18.0
Requires-Dist: tqdm>=4.60.0
Requires-Dist: cftime>=1.5.0
Dynamic: license-file
